odoo/addons/pos_product_cost_security/README.rst
odoo/addons/pos_product_cost_security/__init__.py
odoo/addons/pos_product_cost_security/__manifest__.py
odoo/addons/pos_product_cost_security/i18n/it.po
odoo/addons/pos_product_cost_security/i18n/pos_product_cost_security.pot
odoo/addons/pos_product_cost_security/models/__init__.py
odoo/addons/pos_product_cost_security/models/product_product.py
odoo/addons/pos_product_cost_security/readme/CONTRIBUTORS.rst
odoo/addons/pos_product_cost_security/readme/DESCRIPTION.rst
odoo/addons/pos_product_cost_security/static/description/icon.png
odoo/addons/pos_product_cost_security/static/description/index.html
odoo/addons/pos_product_cost_security/static/src/js/models.js
odoo/addons/pos_product_cost_security/static/tests/tours/tour_pos_product_cost.js
odoo/addons/pos_product_cost_security/tests/__init__.py
odoo/addons/pos_product_cost_security/tests/test_pos_product_cost.py
odoo/addons/pos_product_cost_security/views/assets.xml
odoo14_addon_pos_product_cost_security-14.0.1.0.2.dist-info/METADATA
odoo14_addon_pos_product_cost_security-14.0.1.0.2.dist-info/WHEEL
odoo14_addon_pos_product_cost_security-14.0.1.0.2.dist-info/top_level.txt
odoo14_addon_pos_product_cost_security-14.0.1.0.2.dist-info/RECORD
